lightbt/__init__.py
lightbt/_version.py
lightbt/base.py
lightbt/callbacks.py
lightbt/enums.py
lightbt/portfolio.py
lightbt/position.py
lightbt/signals.py
lightbt/stats.py
lightbt/utils.py
lightbt-0.2.4.dist-info/METADATA
lightbt-0.2.4.dist-info/WHEEL
lightbt-0.2.4.dist-info/licenses/LICENSE
lightbt-0.2.4.dist-info/RECORD
