Metadata-Version: 2.4
Name: lightbt
Version: 0.2.4
Summary: lightweight backtester
Author-email: wukan <wu-kan@163.com>
License: BSD-3-Clause
License-File: LICENSE
Keywords: backtest
Classifier: Development Status :: 4 - Beta
Classifier: Programming Language :: Python
Requires-Python: >=3.7
Requires-Dist: numba>=0.57.1
